{
  "imgUrls": [
    "http://i.imgur.com/3eaivQ5.png"
  ],
  "hasImages": true,
  "contentHTML": "<html><head></head><body><h4>Grid Unique Paths</h4><div><strong>Time: 32:35</strong><br><strong>Score: 375</strong></div><br><br>                      <p>A robot is located at the top-left corner of an <strong>A x B grid</strong> (marked &#x2018;Start&#x2019; in the diagram below).</p><br><br><p><img src=\"math_assets/Q_grid_unique_paths_1.png\" alt=\"Path Sum: Example 1\"></p><br><br><p>The robot can only move either down or right at any point in time. The robot is trying to reach the bottom-right corner of the grid (marked &#x2018;Finish&#x2019; in the diagram below).</p><br><br><p>How many possible unique paths are there?</p><br><br><p><em>Note: A and B will be such that the resulting answer fits in a 32 bit signed integer.</em></p><br><br><p><strong>Example :</strong></p><br><br><div class=\"highlighter-rouge\"><pre class=\"highlight\"><code>Input : A = 2, B = 2<br>Output : 2<br><br>2 possible routes : (0, 0) -&gt; (0, 1) -&gt; (1, 1) <br>              OR  : (0, 0) -&gt; (1, 0) -&gt; (1, 1)<br></code></pre><br></div><br><br><br>                          <blockquote style=\"position:relative;\"><br>                              <span style=\"font-weight: normal;margin: 12px;\"><br>                                  <b>NOTE: </b>You only need to implement the given function. Do not read input, instead use the arguments to the function. Do not print the output, instead return values as specified.<br>                                  Still have a doubt? Checkout <a href=\"/pages/sample_codes/\">Sample Codes</a> for more details.<br>                              </span><br>                            <span class=\"fa fa-remove\" id=\"prob-hint-remove\" style=\"position:absolute;top:0;right:0;margin:12px;color:grey;\"></span><br>                          </blockquote><br><br>                    </body></html>",
  "imgNames": [
    "3eaivQ5.png",
    "Q_grid_unique_paths_1.png"
  ],
  "problem_id": 78,
  "problem_name": "Grid Unique Paths",
  "problem_link": "https://www.interviewbit.com/problems/grid-unique-paths/",
  "problem_score": 375,
  "time_to_solve": "32:35"
}