{
  "contentHTML": "<html><head></head><body><h3>NESTED_CMPL</h3><div><strong>Time: 1:10</strong><br><strong>Score: 20</strong></div><br><br>                      <p>What is the time, space complexity of following code :</p><br><br><div class=\"language-cpp highlighter-rouge\"><pre class=\"highlight\"><code>    <span class=\"kt\">int</span> <span class=\"n\">a</span> <span class=\"o\">=</span> <span class=\"mi\">0</span><span class=\"p\">,</span> <span class=\"n\">b</span> <span class=\"o\">=</span> <span class=\"mi\">0</span><span class=\"p\">;</span>    <br>    <span class=\"k\">for</span> <span class=\"p\">(</span><span class=\"n\">i</span> <span class=\"o\">=</span> <span class=\"mi\">0</span><span class=\"p\">;</span> <span class=\"n\">i</span> <span class=\"o\">&lt;</span> <span class=\"n\">N</span><span class=\"p\">;</span> <span class=\"n\">i</span><span class=\"o\">++</span><span class=\"p\">)</span> <span class=\"p\">{</span><br>        <span class=\"k\">for</span> <span class=\"p\">(</span><span class=\"n\">j</span> <span class=\"o\">=</span> <span class=\"mi\">0</span><span class=\"p\">;</span> <span class=\"n\">j</span> <span class=\"o\">&lt;</span> <span class=\"n\">N</span><span class=\"p\">;</span> <span class=\"n\">j</span><span class=\"o\">++</span><span class=\"p\">)</span> <span class=\"p\">{</span><br>            <span class=\"n\">a</span> <span class=\"o\">=</span> <span class=\"n\">a</span> <span class=\"o\">+</span> <span class=\"n\">j</span><span class=\"p\">;</span><br>        <span class=\"p\">}</span><br>    <span class=\"p\">}</span><br>    <span class=\"k\">for</span> <span class=\"p\">(</span><span class=\"n\">k</span> <span class=\"o\">=</span> <span class=\"mi\">0</span><span class=\"p\">;</span> <span class=\"n\">k</span> <span class=\"o\">&lt;</span> <span class=\"n\">N</span><span class=\"p\">;</span> <span class=\"n\">k</span><span class=\"o\">++</span><span class=\"p\">)</span> <span class=\"p\">{</span><br>        <span class=\"n\">b</span> <span class=\"o\">=</span> <span class=\"n\">b</span> <span class=\"o\">+</span> <span class=\"n\">k</span><span class=\"p\">;</span><br>    <span class=\"p\">}</span> <br></code></pre><br></div><br><br><br>                    </body></html>",
  "hasImages": false,
  "problem_id": 251,
  "problem_link": "https://www.interviewbit.com/problems/nestedcmpl/",
  "problem_name": "NESTED_CMPL",
  "problem_score": 20,
  "time_to_solve": "1:10"
}